wield/model/__init__.py
wield/model/_base.py
wield/model/_version.py
wield/model/optics1064.py
wield/model/base/__init__.py
wield/model/base/dictionary_keys.py
wield/model/base/frequency.py
wield/model/base/frequency_keys.py
wield/model/base/keygroups.py
wield/model/base/optical_frequency.py
wield/model/base/port_types.py
wield/model/base/simulation_object.py
wield/model/base/units.py
wield/model/optics/__init__.py
wield/model/optics/circulator.py
wield/model/optics/laser.py
wield/model/optics/marker.py
wield/model/optics/mirror.py
wield/model/optics/mode_matching.py
wield/model/optics/optical_frequency.py
wield/model/optics/photodiode.py
wield/model/optics/simple_modulators.py
wield/model/optics/space.py
wield/model/optics/squeezer.py
wield/model/optics/substrate_lens.py
wield/model/optics/thin_lens.py
wield/model/optics/vacuum.py
wield/model/optics/alm/__init__.py
wield/model/optics/alm/beam_fit.py
wield/model/optics/alm/beam_param.py
wield/model/optics/alm/substrates.py
wield/model/optics/alm/utils.py
wield/model/optics/test/test_FP.py
wield/model/pgraph/__init__.py
wield/model/pgraph/p_graph.py
wield/model/pgraph/p_graph_impl.py
wield/model/pgraph/p_graph_symbolics.py
wield/model/pgraph/p_object.py
wield/model/pgraph/p_object_schemas.py
wield/model/pgraph/utilities.py
wield/model/pgraph/test/test_pgraph.py
wield/model/pytest/__init__.py
wield/model/registry/__init__.py
wield/model/registry/loader.py
wield/model/system/__init__.py
wield/model/system/algo_AC.py
wield/model/system/algo_DC.py
wield/model/system/algo_bg.py
wield/model/system/algo_freq.py
wield/model/system/algo_graphs.py
wield/model/system/algo_link.py
wield/model/system/algo_log.py
wield/model/system/algo_phys.py
wield/model/system/algo_tups.py
wield/model/system/algo_alm/__init__.py
wield/model/system/algo_alm/algo_alm.py
wield/model/system/algo_alm/algo_mm_linkages.py
wield/model/system/algo_alm/mm_annotate.py
wield/model/system/algo_alm/mm_optimize.py
wield/model/system/algo_alm/mm_overlapper.py
wield.model-0.6.0.dist-info/Apache-2.0.txt
wield.model-0.6.0.dist-info/CC0-1.0.txt
wield.model-0.6.0.dist-info/METADATA
wield.model-0.6.0.dist-info/NOTICE
wield.model-0.6.0.dist-info/WHEEL
wield.model-0.6.0.dist-info/top_level.txt
wield.model-0.6.0.dist-info/RECORD
