Metadata-Version: 2.1
Name: wield.model
Version: 0.6.0
Summary: System description and simulation processing for interferometers, circuits, signals, and control systems
Home-page: https://github.com/wieldphysics/wield-model
Author: Lee McCuller
Author-email: mcculler@caltech.edu
License: Apache-2.0
Project-URL: Bug Tracker, https://github.com/wieldphysics/wield-model/issues
Project-URL: Source Code, https://github.com/wieldphysics/wield-model
Classifier: Intended Audience :: Science/Research
Classifier: License :: OSI Approved :: Apache Software License
Classifier: Operating System :: OS Independent
Classifier: Programming Language :: Python
Classifier: Programming Language :: Python :: 3
Classifier: Topic :: Scientific/Engineering :: Physics
License-File: LICENSES/Apache-2.0.txt
License-File: LICENSES/CC0-1.0.txt
License-File: NOTICE
Requires-Dist: setuptools-scm (>=6.0.0)
Requires-Dist: wield.bunch (>=0.9.1)
Requires-Dist: wield.declarative (>=1.3.3)
Requires-Dist: wield.utilities (>=0.9.1)
Requires-Dist: PyYAML
Requires-Dist: numpy
Requires-Dist: scipy
Requires-Dist: matplotlib
